{
  "session_id": "train_hist_20250915_161728",
  "global_performance": {
    "total_balance": NaN,
    "avg_balance_per_agent": NaN,
    "total_pnl": NaN,
    "avg_pnl_per_agent": NaN,
    "avg_pnl_pct": NaN,
    "total_trades": 635,
    "total_long_trades": 295,
    "total_short_trades": 340,
    "winning_trades": 391,
    "losing_trades": 244,
    "global_win_rate": 61.574803149606296,
    "max_drawdown": Infinity,
    "best_performer": {
      "symbol": "BTCUSDT",
      "pnl_pct": NaN
    },
    "worst_performer": {
      "symbol": "BTCUSDT",
      "pnl_pct": NaN
    },
    "active_agents": 8
  },
  "symbol_performance": {
    "BTCUSDT": {
      "balance": NaN,
      "pnl": NaN,
      "pnl_pct": NaN,
      "trades": 93,
      "win_rate": 59.13978494623656,
      "sharpe_ratio": 0,
      "max_drawdown": Infinity,
      "avg_leverage_used": null
    },
    "ETHUSDT": {
      "balance": NaN,
      "pnl": NaN,
      "pnl_pct": NaN,
      "trades": 143,
      "win_rate": 61.53846153846154,
      "sharpe_ratio": 0,
      "max_drawdown": Infinity,
      "avg_leverage_used": null
    },
    "SOLUSDT": {
      "balance": NaN,
      "pnl": NaN,
      "pnl_pct": NaN,
      "trades": 137,
      "win_rate": 62.04379562043796,
      "sharpe_ratio": 0,
      "max_drawdown": Infinity,
      "avg_leverage_used": null
    },
    "ADAUSDT": {
      "balance": NaN,
      "pnl": NaN,
      "pnl_pct": NaN,
      "trades": 147,
      "win_rate": 58.50340136054422,
      "sharpe_ratio": 0,
      "max_drawdown": Infinity,
      "avg_leverage_used": null
    },
    "XRPUSDT": {
      "balance": 1197.8769946098846,
      "pnl": 197.87699460988458,
      "pnl_pct": 19.78769946098846,
      "trades": 47,
      "win_rate": 68.08510638297872,
      "sharpe_ratio": 0,
      "max_drawdown": 0.0,
      "avg_leverage_used": null
    },
    "DOGEUSDT": {
      "balance": NaN,
      "pnl": NaN,
      "pnl_pct": NaN,
      "trades": 68,
      "win_rate": 66.17647058823529,
      "sharpe_ratio": 0,
      "max_drawdown": Infinity,
      "avg_leverage_used": null
    },
    "PEPEUSDT": {
      "balance": 1000.0,
      "pnl": 0.0,
      "pnl_pct": 0.0,
      "trades": 0,
      "win_rate": 0.0,
      "sharpe_ratio": 0,
      "max_drawdown": 0.0,
      "avg_leverage_used": null
    },
    "SHIBUSDT": {
      "balance": 1000.0,
      "pnl": 0.0,
      "pnl_pct": 0.0,
      "trades": 0,
      "win_rate": 0.0,
      "sharpe_ratio": 0,
      "max_drawdown": 0.0,
      "avg_leverage_used": null
    }
  },
  "telegram_summary": "\ud83c\udfaf <b>Entrenamiento Hist\u00f3rico Completado</b>\n\n\ud83d\udcca <b>Resumen Global:</b>\n\u2022 Duraci\u00f3n: 0.0 minutos\n\u2022 Agentes: 8\n\u2022 Total Trades: 635  (L:295 / S:340)\n\n\ud83d\udcb0 <b>Performance Agregada:</b>\n\u2022 PnL Promedio: $+nan (+nan%)\n\u2022 Win Rate Global: 61.6%\n\u2022 Max Drawdown: inf%\n\n\ud83d\udca1 <b>Rentabilidad (\u00faltimo ciclo):</b> NO RENTABLE  (PnL\u0304 +nan, WR\u0304 72.1%)\n\n\n\ud83d\udcc8 <b>Performance por S\u00edmbolo (ordenado):</b>\n1. <b>BTCUSDT</b>: +nan% (93 trades, 59.1% WR)\n2. <b>ETHUSDT</b>: +nan% (143 trades, 61.5% WR)\n3. <b>SOLUSDT</b>: +nan% (137 trades, 62.0% WR)\n4. <b>ADAUSDT</b>: +nan% (147 trades, 58.5% WR)\n5. <b>XRPUSDT</b>: +19.79% (47 trades, 68.1% WR)\n6. <b>DOGEUSDT</b>: +nan% (68 trades, 66.2% WR)\n7. <b>PEPEUSDT</b>: +0.00% (0 trades, 0.0% WR)\n8. <b>SHIBUSDT</b>: +0.00% (0 trades, 0.0% WR)\n\n\ud83d\udcbe <b>Datos Guardados:</b>\n\u2022 Estrategias por agente: <code>data/agents/{symbol}/strategies.json</code>\n\u2022 Runs completos: <code>data/training_sessions/train_hist_20250915_161728/</code>\n\u2022 Resumen ejecutivo: <code>data/training_sessions/train_hist_20250915_161728/executive_summary.md</code>"
}